{"files":{"apps/backend/dist/domain":{"size":0,"mtime_nanos":0,"mode":0,"is_dir":true},"apps/backend/dist/lib/prisma.js":{"size":231,"mtime_nanos":1784611446168338900,"mode":420,"is_dir":false},"apps/backend/dist/spike":{"size":0,"mtime_nanos":0,"mode":0,"is_dir":true},"apps/backend/dist/spike/testSpike.js":{"size":2521,"mtime_nanos":1784611446262707000,"mode":420,"is_dir":false},"apps/backend/dist/spike/eventStore.js":{"size":1197,"mtime_nanos":1784611446112414000,"mode":420,"is_dir":false},"apps/backend/dist/domain/stateMachine.test.js":{"size":1019,"mtime_nanos":1784611446165688600,"mode":420,"is_dir":false},"apps/backend/dist/repositories":{"size":0,"mtime_nanos":0,"mode":0,"is_dir":true},"apps/backend/dist/services/metrics.services.js":{"size":50,"mtime_nanos":1784611446222419400,"mode":420,"is_dir":false},"apps/backend/dist/services/lock.service.js":{"size":2287,"mtime_nanos":1784545610099345000,"mode":420,"is_dir":false},"apps/backend/dist/services":{"size":0,"mtime_nanos":0,"mode":0,"is_dir":true},"apps/backend/dist/services/order.service.js":{"size":2332,"mtime_nanos":1784545610103355500,"mode":420,"is_dir":false},"apps/backend/dist/spike/server.js":{"size":7435,"mtime_nanos":1784611446160712100,"mode":420,"is_dir":false},"apps/backend/dist/services/order.services.js":{"size":2333,"mtime_nanos":1784611446236417300,"mode":420,"is_dir":false},"apps/backend/dist/index.js":{"size":192,"mtime_nanos":1784611446162697300,"mode":420,"is_dir":false},"apps/backend/dist/lib/redis.js":{"size":331,"mtime_nanos":1784611446170865800,"mode":420,"is_dir":false},"apps/backend/.turbo/turbo-build.log":{"size":352,"mtime_nanos":1784611450046631400,"mode":420,"is_dir":false},"apps/backend/dist/services/lock.services.js":{"size":2293,"mtime_nanos":1784611446215508200,"mode":420,"is_dir":false},"apps/backend/dist/domain/stateMachine.js":{"size":749,"mtime_nanos":1784611446134559600,"mode":420,"is_dir":false},"apps/backend/dist/lib":{"size":0,"mtime_nanos":0,"mode":0,"is_dir":true},"apps/backend/dist/spike/client.js":{"size":3109,"mtime_nanos":1784611446253817700,"mode":420,"is_dir":false},"apps/backend/dist/types":{"size":0,"mtime_nanos":0,"mode":0,"is_dir":true},"apps/backend/dist/types/events.js":{"size":35,"mtime_nanos":1784611446238869700,"mode":420,"is_dir":false},"apps/backend/dist/repositories/order.repository.js":{"size":4102,"mtime_nanos":1784611446202931800,"mode":420,"is_dir":false},"apps/backend/dist":{"size":0,"mtime_nanos":0,"mode":0,"is_dir":true}},"order":["apps/backend/.turbo/turbo-build.log","apps/backend/dist","apps/backend/dist/domain","apps/backend/dist/domain/stateMachine.js","apps/backend/dist/domain/stateMachine.test.js","apps/backend/dist/index.js","apps/backend/dist/lib","apps/backend/dist/lib/prisma.js","apps/backend/dist/lib/redis.js","apps/backend/dist/repositories","apps/backend/dist/repositories/order.repository.js","apps/backend/dist/services","apps/backend/dist/services/lock.service.js","apps/backend/dist/services/lock.services.js","apps/backend/dist/services/metrics.services.js","apps/backend/dist/services/order.service.js","apps/backend/dist/services/order.services.js","apps/backend/dist/spike","apps/backend/dist/spike/client.js","apps/backend/dist/spike/eventStore.js","apps/backend/dist/spike/server.js","apps/backend/dist/spike/testSpike.js","apps/backend/dist/types","apps/backend/dist/types/events.js"]}